multiplex/__init__.py
multiplex/actions.py
multiplex/ansi.py
multiplex/box.py
multiplex/buffer.py
multiplex/commands.py
multiplex/controller.py
multiplex/enums.py
multiplex/exceptions.py
multiplex/export.py
multiplex/help.py
multiplex/ipc.py
multiplex/iterator.py
multiplex/keys.py
multiplex/keys_input.py
multiplex/log.py
multiplex/main.py
multiplex/multiplex.py
multiplex/process.py
multiplex/refs.py
multiplex/resize.py
multiplex/viewer.py
multiplex-0.6.1.dist-info/entry_points.txt
multiplex-0.6.1.dist-info/LICENSE
multiplex-0.6.1.dist-info/WHEEL
multiplex-0.6.1.dist-info/METADATA
multiplex-0.6.1.dist-info/RECORD
