Metadata-Version: 2.1
Name: multiplex
Version: 0.6.1
Summary: View output of multiple processes, in parallel, in the console, with an interactive TUI
Home-page: https://github.com/dankilman/multiplex
License: MIT
Author: Dan Kilman
Author-email: dankilman@gmail.com
Requires-Python: >=3.7,<4.0
Classifier: License :: OSI Approved :: MIT License
Classifier: Programming Language :: Python :: 3
Classifier: Programming Language :: Python :: 3.7
Classifier: Programming Language :: Python :: 3.8
Classifier: Programming Language :: Python :: 3.9
Classifier: Programming Language :: Python :: 3.10
Classifier: Programming Language :: Python :: 3.11
Requires-Dist: aiofiles (>=0.5.0,<0.6.0)
Requires-Dist: aiostream (>=0.4.1,<0.5.0)
Requires-Dist: click (>=7.1.2)
Requires-Dist: easy-ansi (>=0.3,<0.4)
Requires-Dist: pyte (>=0.8.0,<0.9.0)
Project-URL: Repository, https://github.com/dankilman/multiplex
